paper_trackr/__init__.py
paper_trackr/main.py
paper_trackr/config/__init__.py
paper_trackr/config/global_settings.py
paper_trackr/core/actions.py
paper_trackr/core/biorxiv_request.py
paper_trackr/core/configure_email.py
paper_trackr/core/db_utils.py
paper_trackr/core/epmc_request.py
paper_trackr/core/generate_color.py
paper_trackr/core/generate_tldr.py
paper_trackr/core/mailer.py
paper_trackr/core/manage_query.py
paper_trackr/core/pubmed_request.py
paper_trackr/database/.keep
paper_trackr/database/articles.db
paper_trackr/database/history.csv
paper_trackr/scitldr/data/multiprocessing_bpe_encoder.py
paper_trackr/scitldr/scripts/generate.py
paper_trackr/templates/newsletter_template.html
paper_trackr-1.0.14.dist-info/licenses/LICENSE
paper_trackr-1.0.14.dist-info/METADATA
paper_trackr-1.0.14.dist-info/WHEEL
paper_trackr-1.0.14.dist-info/entry_points.txt
paper_trackr-1.0.14.dist-info/top_level.txt
paper_trackr-1.0.14.dist-info/RECORD
