Metadata-Version: 2.4
Name: paper-trackr
Version: 1.0.14
Summary: Track recently published papers from PubMed, EuropePMC and bioRxiv.
Author-email: Felipe Vaz Peres <felipe.vzps@gmail.com>
License-Expression: MIT
Project-URL: Homepage, https://github.com/felipevzps/paper-trackr
Project-URL: Issues, https://github.com/felipevzps/paper-trackr/issues
Requires-Python: >=3.11
License-File: LICENSE
Requires-Dist: feedparser>=6.0.11
Requires-Dist: PyYAML>=6.0.2
Requires-Dist: questionary>=2.1.0
Requires-Dist: requests>=2.32.3
Dynamic: license-file
